README.txt
distribute_setup.py
run_scipysim
setup.py
ScipySim.egg-info/PKG-INFO
ScipySim.egg-info/SOURCES.txt
ScipySim.egg-info/dependency_links.txt
ScipySim.egg-info/requires.txt
ScipySim.egg-info/top_level.txt
scipysim/__init__.py
scipysim/test_scipysim.py
scipysim/actors/__init__.py
scipysim/actors/display/__init__.py
scipysim/actors/display/bundleHistPlotter.py
scipysim/actors/display/bundlePlotter.py
scipysim/actors/display/plotter.py
scipysim/actors/display/stemmer.py
scipysim/actors/display/test_display.py
scipysim/actors/io/VideoSnapshot.py
scipysim/actors/io/__init__.py
scipysim/actors/io/bundle.py
scipysim/actors/io/reader.py
scipysim/actors/io/test_io.py
scipysim/actors/io/unbundle.py
scipysim/actors/io/writer.py
scipysim/actors/logic/__init__.py
scipysim/actors/logic/compare.py
scipysim/actors/logic/greaterthan.py
scipysim/actors/logic/lessthan.py
scipysim/actors/logic/passthrough.py
scipysim/actors/logic/testlogic.py
scipysim/actors/math/__init__.py
scipysim/actors/math/abs.py
scipysim/actors/math/constant.py
scipysim/actors/math/ct_integrator.py
scipysim/actors/math/ct_integrator_de1.py
scipysim/actors/math/derivative.py
scipysim/actors/math/dt_integrator.py
scipysim/actors/math/proportional.py
scipysim/actors/math/subtract.py
scipysim/actors/math/summer.py
scipysim/actors/math/testmath.py
scipysim/actors/math/trig/CTSinGenerator.py
scipysim/actors/math/trig/DTSinGenerator.py
scipysim/actors/math/trig/__init__.py
scipysim/actors/math/trig/sin.py
scipysim/actors/signal/__init__.py
scipysim/actors/signal/copier.py
scipysim/actors/signal/decimator.py
scipysim/actors/signal/delay.py
scipysim/actors/signal/eventfilter.py
scipysim/actors/signal/interpolator.py
scipysim/actors/signal/quantizer.py
scipysim/actors/signal/ramp.py
scipysim/actors/signal/random_signal.py
scipysim/actors/signal/sampler.py
scipysim/actors/signal/step.py
scipysim/actors/signal/testsignal.py
scipysim/actors/strings/__init__.py
scipysim/actors/strings/intparser.py
scipysim/actors/strings/teststring.py
scipysim/core/__init__.py
scipysim/core/actor.py
scipysim/core/channel.py
scipysim/core/errors.py
scipysim/core/event.py
