Metadata-Version: 1.0
Name: ScipySim
Version: 0.1.5
Summary: Simulation in Python.
Home-page: http://code.google.com/p/scipy-sim/
Author: Brian Thorne, Allan McInnes
Author-email: hardbyte@gmail.com
License: GPLv3
Keywords: simulation,scipy,discrete events
Platform: UNKNOWN
Classifier: Programming Language :: Python :: 2.6
Classifier: Development Status :: 3 - Alpha
Classifier: Environment :: Console
Classifier: Intended Audience :: Science/Research
Classifier: License :: OSI Approved :: GNU General Public License (GPL)
Classifier: Operating System :: OS Independent
Classifier: Topic :: Scientific/Engineering
